[{"game_id": 24736, "begin_at": "2020-08-02 11:33:39+00:00", "timestamp": 1596368019, "year": 2020, "month": 8, "day": 2, "weekday": 6, "hour": 11, "map_id": 2, "team_id": 127044, "player_id": 26689, "team_opponent_id": 127690, "player_opponent_id": 29507, "adr": 81.1, "assists": 3, "deaths": 16, "first_kills_diff": -2, "flash_assists": 0, "headshots": 11, "k_d_diff": 2, "kast": 69.6, "kills": 18, "rating": 1.18, "start_ct": 0, "total_rounds": 23, "win": 1, "r1_win": 0, "r2_win": 0, "r16_win": 0, "r17_win": 0, "h1_win_round_count": 10, "h2_win_round_count": 6, "h1_eliminated_count": 9, "h1_exploded_count": 4, "h1_defused_count": 2, "h1_timeout_count": 0, "h2_eliminated_count": 7, "h2_exploded_count": 0, "h2_defused_count": 0, "h2_timeout_count": 1}, {"game_id": 24736, "begin_at": "2020-08-02 11:33:39+00:00", "timestamp": 1596368019, "year": 2020, "month": 8, "day": 2, "weekday": 6, "hour": 11, "map_id": 2, "team_id": 127044, "player_id": 26689, "team_opponent_id": 127690, "player_opponent_id": 29508, "adr": 81.1, "assists": 3, "deaths": 16, "first_kills_diff": -2, "flash_assists": 0, "headshots": 11, "k_d_diff": 2, "kast": 69.6, "kills": 18, "rating": 1.18, "start_ct": 0, "total_rounds": 23, "win": 1, "r1_win": 0, "r2_win": 0, "r16_win": 0, "r17_win": 0, "h1_win_round_count": 10, "h2_win_round_count": 6, "h1_eliminated_count": 9, "h1_exploded_count": 4, "h1_defused_count": 2, "h1_timeout_count": 0, "h2_eliminated_count": 7, "h2_exploded_count": 0, "h2_defused_count": 0, "h2_timeout_count": 1}, {"game_id": 24736, "begin_at": "2020-08-02 11:33:39+00:00", "timestamp": 1596368019, "year": 2020, "month": 8, "day": 2, "weekday": 6, "hour": 11, "map_id": 2, "team_id": 127044, "player_id": 26689, "team_opponent_id": 127690, "player_opponent_id": 29509, "adr": 81.1, "assists": 3, "deaths": 16, "first_kills_diff": -2, "flash_assists": 0, "headshots": 11, "k_d_diff": 2, "kast": 69.6, "kills": 18, "rating": 1.18, "start_ct": 0, "total_rounds": 23, "win": 1, "r1_win": 0, "r2_win": 0, "r16_win": 0, "r17_win": 0, "h1_win_round_count": 10, "h2_win_round_count": 6, "h1_eliminated_count": 9, "h1_exploded_count": 4, "h1_defused_count": 2, "h1_timeout_count": 0, "h2_eliminated_count": 7, "h2_exploded_count": 0, "h2_defused_count": 0, "h2_timeout_count": 1}, {"game_id": 24736, "begin_at": "2020-08-02 11:33:39+00:00", "timestamp": 1596368019, "year": 2020, "month": 8, "day": 2, "weekday": 6, "hour": 11, "map_id": 2, "team_id": 127044, "player_id": 26689, "team_opponent_id": 127690, "player_opponent_id": 29510, "adr": 81.1, "assists": 3, "deaths": 16, "first_kills_diff": -2, "flash_assists": 0, "headshots": 11, "k_d_diff": 2, "kast": 69.6, "kills": 18, "rating": 1.18, "start_ct": 0, "total_rounds": 23, "win": 1, "r1_win": 0, "r2_win": 0, "r16_win": 0, "r17_win": 0, "h1_win_round_count": 10, "h2_win_round_count": 6, "h1_eliminated_count": 9, "h1_exploded_count": 4, "h1_defused_count": 2, "h1_timeout_count": 0, "h2_eliminated_count": 7, "h2_exploded_count": 0, "h2_defused_count": 0, "h2_timeout_count": 1}, {"game_id": 24736, "begin_at": "2020-08-02 11:33:39+00:00", "timestamp": 1596368019, "year": 2020, "month": 8, "day": 2, "weekday": 6, "hour": 11, "map_id": 2, "team_id": 127044, "player_id": 26689, "team_opponent_id": 127690, "player_opponent_id": 29511, "adr": 81.1, "assists": 3, "deaths": 16, "first_kills_diff": -2, "flash_assists": 0, "headshots": 11, "k_d_diff": 2, "kast": 69.6, "kills": 18, "rating": 1.18, "start_ct": 0, "total_rounds": 23, "win": 1, "r1_win": 0, "r2_win": 0, "r16_win": 0, "r17_win": 0, "h1_win_round_count": 10, "h2_win_round_count": 6, "h1_eliminated_count": 9, "h1_exploded_count": 4, "h1_defused_count": 2, "h1_timeout_count": 0, "h2_eliminated_count": 7, "h2_exploded_count": 0, "h2_defused_count": 0, "h2_timeout_count": 1}, {"game_id": 24736, "begin_at": "2020-08-02 11:33:39+00:00", "timestamp": 1596368019, "year": 2020, "month": 8, "day": 2, "weekday": 6, "hour": 11, "map_id": 2, "team_id": 127044, "player_id": 26690, "team_opponent_id": 127690, "player_opponent_id": 29507, "adr": 105.4, "assists": 1, "deaths": 14, "first_kills_diff": 1, "flash_assists": 0, "headshots": 14, "k_d_diff": 10, "kast": 78.3, "kills": 24, "rating": 1.6, "start_ct": 0, "total_rounds": 23, "win": 1, "r1_win": 0, "r2_win": 0, "r16_win": 0, "r17_win": 0, "h1_win_round_count": 10, "h2_win_round_count": 6, "h1_eliminated_count": 9, "h1_exploded_count": 4, "h1_defused_count": 2, "h1_timeout_count": 0, "h2_eliminated_count": 7, "h2_exploded_count": 0, "h2_defused_count": 0, "h2_timeout_count": 1}, {"game_id": 24736, "begin_at": "2020-08-02 11:33:39+00:00", "timestamp": 1596368019, "year": 2020, "month": 8, "day": 2, "weekday": 6, "hour": 11, "map_id": 2, "team_id": 127044, "player_id": 26690, "team_opponent_id": 127690, "player_opponent_id": 29508, "adr": 105.4, "assists": 1, "deaths": 14, "first_kills_diff": 1, "flash_assists": 0, "headshots": 14, "k_d_diff": 10, "kast": 78.3, "kills": 24, "rating": 1.6, "start_ct": 0, "total_rounds": 23, "win": 1, "r1_win": 0, "r2_win": 0, "r16_win": 0, "r17_win": 0, "h1_win_round_count": 10, "h2_win_round_count": 6, "h1_eliminated_count": 9, "h1_exploded_count": 4, "h1_defused_count": 2, "h1_timeout_count": 0, "h2_eliminated_count": 7, "h2_exploded_count": 0, "h2_defused_count": 0, "h2_timeout_count": 1}, {"game_id": 24736, "begin_at": "2020-08-02 11:33:39+00:00", "timestamp": 1596368019, "year": 2020, "month": 8, "day": 2, "weekday": 6, "hour": 11, "map_id": 2, "team_id": 127044, "player_id": 26690, "team_opponent_id": 127690, "player_opponent_id": 29509, "adr": 105.4, "assists": 1, "deaths": 14, "first_kills_diff": 1, "flash_assists": 0, "headshots": 14, "k_d_diff": 10, "kast": 78.3, "kills": 24, "rating": 1.6, "start_ct": 0, "total_rounds": 23, "win": 1, "r1_win": 0, "r2_win": 0, "r16_win": 0, "r17_win": 0, "h1_win_round_count": 10, "h2_win_round_count": 6, "h1_eliminated_count": 9, "h1_exploded_count": 4, "h1_defused_count": 2, "h1_timeout_count": 0, "h2_eliminated_count": 7, "h2_exploded_count": 0, "h2_defused_count": 0, "h2_timeout_count": 1}, {"game_id": 24736, "begin_at": "2020-08-02 11:33:39+00:00", "timestamp": 1596368019, "year": 2020, "month": 8, "day": 2, "weekday": 6, "hour": 11, "map_id": 2, "team_id": 127044, "player_id": 26690, "team_opponent_id": 127690, "player_opponent_id": 29510, "adr": 105.4, "assists": 1, "deaths": 14, "first_kills_diff": 1, "flash_assists": 0, "headshots": 14, "k_d_diff": 10, "kast": 78.3, "kills": 24, "rating": 1.6, "start_ct": 0, "total_rounds": 23, "win": 1, "r1_win": 0, "r2_win": 0, "r16_win": 0, "r17_win": 0, "h1_win_round_count": 10, "h2_win_round_count": 6, "h1_eliminated_count": 9, "h1_exploded_count": 4, "h1_defused_count": 2, "h1_timeout_count": 0, "h2_eliminated_count": 7, "h2_exploded_count": 0, "h2_defused_count": 0, "h2_timeout_count": 1}, {"game_id": 24736, "begin_at": "2020-08-02 11:33:39+00:00", "timestamp": 1596368019, "year": 2020, "month": 8, "day": 2, "weekday": 6, "hour": 11, "map_id": 2, "team_id": 127044, "player_id": 26690, "team_opponent_id": 127690, "player_opponent_id": 29511, "adr": 105.4, "assists": 1, "deaths": 14, "first_kills_diff": 1, "flash_assists": 0, "headshots": 14, "k_d_diff": 10, "kast": 78.3, "kills": 24, "rating": 1.6, "start_ct": 0, "total_rounds": 23, "win": 1, "r1_win": 0, "r2_win": 0, "r16_win": 0, "r17_win": 0, "h1_win_round_count": 10, "h2_win_round_count": 6, "h1_eliminated_count": 9, "h1_exploded_count": 4, "h1_defused_count": 2, "h1_timeout_count": 0, "h2_eliminated_count": 7, "h2_exploded_count": 0, "h2_defused_count": 0, "h2_timeout_count": 1}, {"game_id": 24736, "begin_at": "2020-08-02 11:33:39+00:00", "timestamp": 1596368019, "year": 2020, "month": 8, "day": 2, "weekday": 6, "hour": 11, "map_id": 2, "team_id": 127044, "player_id": 26691, "team_opponent_id": 127690, "player_opponent_id": 29507, "adr": 76.3, "assists": 3, "deaths": 9, "first_kills_diff": 2, "flash_assists": 0, "headshots": 5, "k_d_diff": 3, "kast": 82.6, "kills": 12, "rating": 1.23, "start_ct": 0, "total_rounds": 23, "win": 1, "r1_win": 0, "r2_win": 0, "r16_win": 0, "r17_win": 0, "h1_win_round_count": 10, "h2_win_round_count": 6, "h1_eliminated_count": 9, "h1_exploded_count": 4, "h1_defused_count": 2, "h1_timeout_count": 0, "h2_eliminated_count": 7, "h2_exploded_count": 0, "h2_defused_count": 0, "h2_timeout_count": 1}, {"game_id": 24736, "begin_at": "2020-08-02 11:33:39+00:00", "timestamp": 1596368019, "year": 2020, "month": 8, "day": 2, "weekday": 6, "hour": 11, "map_id": 2, "team_id": 127044, "player_id": 26691, "team_opponent_id": 127690, "player_opponent_id": 29508, "adr": 76.3, "assists": 3, "deaths": 9, "first_kills_diff": 2, "flash_assists": 0, "headshots": 5, "k_d_diff": 3, "kast": 82.6, "kills": 12, "rating": 1.23, "start_ct": 0, "total_rounds": 23, "win": 1, "r1_win": 0, "r2_win": 0, "r16_win": 0, "r17_win": 0, "h1_win_round_count": 10, "h2_win_round_count": 6, "h1_eliminated_count": 9, "h1_exploded_count": 4, "h1_defused_count": 2, "h1_timeout_count": 0, "h2_eliminated_count": 7, "h2_exploded_count": 0, "h2_defused_count": 0, "h2_timeout_count": 1}, {"game_id": 24736, "begin_at": "2020-08-02 11:33:39+00:00", "timestamp": 1596368019, "year": 2020, "month": 8, "day": 2, "weekday": 6, "hour": 11, "map_id": 2, "team_id": 127044, "player_id": 26691, "team_opponent_id": 127690, "player_opponent_id": 29509, "adr": 76.3, "assists": 3, "deaths": 9, "first_kills_diff": 2, "flash_assists": 0, "headshots": 5, "k_d_diff": 3, "kast": 82.6, "kills": 12, "rating": 1.23, "start_ct": 0, "total_rounds": 23, "win": 1, "r1_win": 0, "r2_win": 0, "r16_win": 0, "r17_win": 0, "h1_win_round_count": 10, "h2_win_round_count": 6, "h1_eliminated_count": 9, "h1_exploded_count": 4, "h1_defused_count": 2, "h1_timeout_count": 0, "h2_eliminated_count": 7, "h2_exploded_count": 0, "h2_defused_count": 0, "h2_timeout_count": 1}, {"game_id": 24736, "begin_at": "2020-08-02 11:33:39+00:00", "timestamp": 1596368019, "year": 2020, "month": 8, "day": 2, "weekday": 6, "hour": 11, "map_id": 2, "team_id": 127044, "player_id": 26691, "team_opponent_id": 127690, "player_opponent_id": 29510, "adr": 76.3, "assists": 3, "deaths": 9, "first_kills_diff": 2, "flash_assists": 0, "headshots": 5, "k_d_diff": 3, "kast": 82.6, "kills": 12, "rating": 1.23, "start_ct": 0, "total_rounds": 23, "win": 1, "r1_win": 0, "r2_win": 0, "r16_win": 0, "r17_win": 0, "h1_win_round_count": 10, "h2_win_round_count": 6, "h1_eliminated_count": 9, "h1_exploded_count": 4, "h1_defused_count": 2, "h1_timeout_count": 0, "h2_eliminated_count": 7, "h2_exploded_count": 0, "h2_defused_count": 0, "h2_timeout_count": 1}, {"game_id": 24736, "begin_at": "2020-08-02 11:33:39+00:00", "timestamp": 1596368019, "year": 2020, "month": 8, "day": 2, "weekday": 6, "hour": 11, "map_id": 2, "team_id": 127044, "player_id": 26691, "team_opponent_id": 127690, "player_opponent_id": 29511, "adr": 76.3, "assists": 3, "deaths": 9, "first_kills_diff": 2, "flash_assists": 0, "headshots": 5, "k_d_diff": 3, "kast": 82.6, "kills": 12, "rating": 1.23, "start_ct": 0, "total_rounds": 23, "win": 1, "r1_win": 0, "r2_win": 0, "r16_win": 0, "r17_win": 0, "h1_win_round_count": 10, "h2_win_round_count": 6, "h1_eliminated_count": 9, "h1_exploded_count": 4, "h1_defused_count": 2, "h1_timeout_count": 0, "h2_eliminated_count": 7, "h2_exploded_count": 0, "h2_defused_count": 0, "h2_timeout_count": 1}, {"game_id": 24736, "begin_at": "2020-08-02 11:33:39+00:00", "timestamp": 1596368019, "year": 2020, "month": 8, "day": 2, "weekday": 6, "hour": 11, "map_id": 2, "team_id": 127044, "player_id": 26692, "team_opponent_id": 127690, "player_opponent_id": 29507, "adr": 57.6, "assists": 2, "deaths": 11, "first_kills_diff": 0, "flash_assists": 0, "headshots": 11, "k_d_diff": 2, "kast": 82.6, "kills": 13, "rating": 1.18, "start_ct": 0, "total_rounds": 23, "win": 1, "r1_win": 0, "r2_win": 0, "r16_win": 0, "r17_win": 0, "h1_win_round_count": 10, "h2_win_round_count": 6, "h1_eliminated_count": 9, "h1_exploded_count": 4, "h1_defused_count": 2, "h1_timeout_count": 0, "h2_eliminated_count": 7, "h2_exploded_count": 0, "h2_defused_count": 0, "h2_timeout_count": 1}, {"game_id": 24736, "begin_at": "2020-08-02 11:33:39+00:00", "timestamp": 1596368019, "year": 2020, "month": 8, "day": 2, "weekday": 6, "hour": 11, "map_id": 2, "team_id": 127044, "player_id": 26692, "team_opponent_id": 127690, "player_opponent_id": 29508, "adr": 57.6, "assists": 2, "deaths": 11, "first_kills_diff": 0, "flash_assists": 0, "headshots": 11, "k_d_diff": 2, "kast": 82.6, "kills": 13, "rating": 1.18, "start_ct": 0, "total_rounds": 23, "win": 1, "r1_win": 0, "r2_win": 0, "r16_win": 0, "r17_win": 0, "h1_win_round_count": 10, "h2_win_round_count": 6, "h1_eliminated_count": 9, "h1_exploded_count": 4, "h1_defused_count": 2, "h1_timeout_count": 0, "h2_eliminated_count": 7, "h2_exploded_count": 0, "h2_defused_count": 0, "h2_timeout_count": 1}, {"game_id": 24736, "begin_at": "2020-08-02 11:33:39+00:00", "timestamp": 1596368019, "year": 2020, "month": 8, "day": 2, "weekday": 6, "hour": 11, "map_id": 2, "team_id": 127044, "player_id": 26692, "team_opponent_id": 127690, "player_opponent_id": 29509, "adr": 57.6, "assists": 2, "deaths": 11, "first_kills_diff": 0, "flash_assists": 0, "headshots": 11, "k_d_diff": 2, "kast": 82.6, "kills": 13, "rating": 1.18, "start_ct": 0, "total_rounds": 23, "win": 1, "r1_win": 0, "r2_win": 0, "r16_win": 0, "r17_win": 0, "h1_win_round_count": 10, "h2_win_round_count": 6, "h1_eliminated_count": 9, "h1_exploded_count": 4, "h1_defused_count": 2, "h1_timeout_count": 0, "h2_eliminated_count": 7, "h2_exploded_count": 0, "h2_defused_count": 0, "h2_timeout_count": 1}, {"game_id": 24736, "begin_at": "2020-08-02 11:33:39+00:00", "timestamp": 1596368019, "year": 2020, "month": 8, "day": 2, "weekday": 6, "hour": 11, "map_id": 2, "team_id": 127044, "player_id": 26692, "team_opponent_id": 127690, "player_opponent_id": 29510, "adr": 57.6, "assists": 2, "deaths": 11, "first_kills_diff": 0, "flash_assists": 0, "headshots": 11, "k_d_diff": 2, "kast": 82.6, "kills": 13, "rating": 1.18, "start_ct": 0, "total_rounds": 23, "win": 1, "r1_win": 0, "r2_win": 0, "r16_win": 0, "r17_win": 0, "h1_win_round_count": 10, "h2_win_round_count": 6, "h1_eliminated_count": 9, "h1_exploded_count": 4, "h1_defused_count": 2, "h1_timeout_count": 0, "h2_eliminated_count": 7, "h2_exploded_count": 0, "h2_defused_count": 0, "h2_timeout_count": 1}, {"game_id": 24736, "begin_at": "2020-08-02 11:33:39+00:00", "timestamp": 1596368019, "year": 2020, "month": 8, "day": 2, "weekday": 6, "hour": 11, "map_id": 2, "team_id": 127044, "player_id": 26692, "team_opponent_id": 127690, "player_opponent_id": 29511, "adr": 57.6, "assists": 2, "deaths": 11, "first_kills_diff": 0, "flash_assists": 0, "headshots": 11, "k_d_diff": 2, "kast": 82.6, "kills": 13, "rating": 1.18, "start_ct": 0, "total_rounds": 23, "win": 1, "r1_win": 0, "r2_win": 0, "r16_win": 0, "r17_win": 0, "h1_win_round_count": 10, "h2_win_round_count": 6, "h1_eliminated_count": 9, "h1_exploded_count": 4, "h1_defused_count": 2, "h1_timeout_count": 0, "h2_eliminated_count": 7, "h2_exploded_count": 0, "h2_defused_count": 0, "h2_timeout_count": 1}, {"game_id": 24736, "begin_at": "2020-08-02 11:33:39+00:00", "timestamp": 1596368019, "year": 2020, "month": 8, "day": 2, "weekday": 6, "hour": 11, "map_id": 2, "team_id": 127044, "player_id": 26693, "team_opponent_id": 127690, "player_opponent_id": 29507, "adr": 63.0, "assists": 2, "deaths": 10, "first_kills_diff": 0, "flash_assists": 0, "headshots": 7, "k_d_diff": 5, "kast": 73.9, "kills": 15, "rating": 1.11, "start_ct": 0, "total_rounds": 23, "win": 1, "r1_win": 0, "r2_win": 0, "r16_win": 0, "r17_win": 0, "h1_win_round_count": 10, "h2_win_round_count": 6, "h1_eliminated_count": 9, "h1_exploded_count": 4, "h1_defused_count": 2, "h1_timeout_count": 0, "h2_eliminated_count": 7, "h2_exploded_count": 0, "h2_defused_count": 0, "h2_timeout_count": 1}, {"game_id": 24736, "begin_at": "2020-08-02 11:33:39+00:00", "timestamp": 1596368019, "year": 2020, "month": 8, "day": 2, "weekday": 6, "hour": 11, "map_id": 2, "team_id": 127044, "player_id": 26693, "team_opponent_id": 127690, "player_opponent_id": 29508, "adr": 63.0, "assists": 2, "deaths": 10, "first_kills_diff": 0, "flash_assists": 0, "headshots": 7, "k_d_diff": 5, "kast": 73.9, "kills": 15, "rating": 1.11, "start_ct": 0, "total_rounds": 23, "win": 1, "r1_win": 0, "r2_win": 0, "r16_win": 0, "r17_win": 0, "h1_win_round_count": 10, "h2_win_round_count": 6, "h1_eliminated_count": 9, "h1_exploded_count": 4, "h1_defused_count": 2, "h1_timeout_count": 0, "h2_eliminated_count": 7, "h2_exploded_count": 0, "h2_defused_count": 0, "h2_timeout_count": 1}, {"game_id": 24736, "begin_at": "2020-08-02 11:33:39+00:00", "timestamp": 1596368019, "year": 2020, "month": 8, "day": 2, "weekday": 6, "hour": 11, "map_id": 2, "team_id": 127044, "player_id": 26693, "team_opponent_id": 127690, "player_opponent_id": 29509, "adr": 63.0, "assists": 2, "deaths": 10, "first_kills_diff": 0, "flash_assists": 0, "headshots": 7, "k_d_diff": 5, "kast": 73.9, "kills": 15, "rating": 1.11, "start_ct": 0, "total_rounds": 23, "win": 1, "r1_win": 0, "r2_win": 0, "r16_win": 0, "r17_win": 0, "h1_win_round_count": 10, "h2_win_round_count": 6, "h1_eliminated_count": 9, "h1_exploded_count": 4, "h1_defused_count": 2, "h1_timeout_count": 0, "h2_eliminated_count": 7, "h2_exploded_count": 0, "h2_defused_count": 0, "h2_timeout_count": 1}, {"game_id": 24736, "begin_at": "2020-08-02 11:33:39+00:00", "timestamp": 1596368019, "year": 2020, "month": 8, "day": 2, "weekday": 6, "hour": 11, "map_id": 2, "team_id": 127044, "player_id": 26693, "team_opponent_id": 127690, "player_opponent_id": 29510, "adr": 63.0, "assists": 2, "deaths": 10, "first_kills_diff": 0, "flash_assists": 0, "headshots": 7, "k_d_diff": 5, "kast": 73.9, "kills": 15, "rating": 1.11, "start_ct": 0, "total_rounds": 23, "win": 1, "r1_win": 0, "r2_win": 0, "r16_win": 0, "r17_win": 0, "h1_win_round_count": 10, "h2_win_round_count": 6, "h1_eliminated_count": 9, "h1_exploded_count": 4, "h1_defused_count": 2, "h1_timeout_count": 0, "h2_eliminated_count": 7, "h2_exploded_count": 0, "h2_defused_count": 0, "h2_timeout_count": 1}, {"game_id": 24736, "begin_at": "2020-08-02 11:33:39+00:00", "timestamp": 1596368019, "year": 2020, "month": 8, "day": 2, "weekday": 6, "hour": 11, "map_id": 2, "team_id": 127044, "player_id": 26693, "team_opponent_id": 127690, "player_opponent_id": 29511, "adr": 63.0, "assists": 2, "deaths": 10, "first_kills_diff": 0, "flash_assists": 0, "headshots": 7, "k_d_diff": 5, "kast": 73.9, "kills": 15, "rating": 1.11, "start_ct": 0, "total_rounds": 23, "win": 1, "r1_win": 0, "r2_win": 0, "r16_win": 0, "r17_win": 0, "h1_win_round_count": 10, "h2_win_round_count": 6, "h1_eliminated_count": 9, "h1_exploded_count": 4, "h1_defused_count": 2, "h1_timeout_count": 0, "h2_eliminated_count": 7, "h2_exploded_count": 0, "h2_defused_count": 0, "h2_timeout_count": 1}, {"game_id": 24736, "begin_at": "2020-08-02 11:33:39+00:00", "timestamp": 1596368019, "year": 2020, "month": 8, "day": 2, "weekday": 6, "hour": 11, "map_id": 2, "team_id": 127690, "player_id": 29507, "team_opponent_id": 127044, "player_opponent_id": 26689, "adr": 86.0, "assists": 3, "deaths": 15, "first_kills_diff": 0, "flash_assists": 0, "headshots": 8, "k_d_diff": -1, "kast": 65.2, "kills": 14, "rating": 1.1, "start_ct": 1, "total_rounds": 23, "win": 0, "r1_win": 1, "r2_win": 1, "r16_win": 1, "r17_win": 1, "h1_win_round_count": 5, "h2_win_round_count": 2, "h1_eliminated_count": 9, "h1_exploded_count": 4, "h1_defused_count": 2, "h1_timeout_count": 0, "h2_eliminated_count": 7, "h2_exploded_count": 0, "h2_defused_count": 0, "h2_timeout_count": 1}, {"game_id": 24736, "begin_at": "2020-08-02 11:33:39+00:00", "timestamp": 1596368019, "year": 2020, "month": 8, "day": 2, "weekday": 6, "hour": 11, "map_id": 2, "team_id": 127690, "player_id": 29507, "team_opponent_id": 127044, "player_opponent_id": 26690, "adr": 86.0, "assists": 3, "deaths": 15, "first_kills_diff": 0, "flash_assists": 0, "headshots": 8, "k_d_diff": -1, "kast": 65.2, "kills": 14, "rating": 1.1, "start_ct": 1, "total_rounds": 23, "win": 0, "r1_win": 1, "r2_win": 1, "r16_win": 1, "r17_win": 1, "h1_win_round_count": 5, "h2_win_round_count": 2, "h1_eliminated_count": 9, "h1_exploded_count": 4, "h1_defused_count": 2, "h1_timeout_count": 0, "h2_eliminated_count": 7, "h2_exploded_count": 0, "h2_defused_count": 0, "h2_timeout_count": 1}, {"game_id": 24736, "begin_at": "2020-08-02 11:33:39+00:00", "timestamp": 1596368019, "year": 2020, "month": 8, "day": 2, "weekday": 6, "hour": 11, "map_id": 2, "team_id": 127690, "player_id": 29507, "team_opponent_id": 127044, "player_opponent_id": 26691, "adr": 86.0, "assists": 3, "deaths": 15, "first_kills_diff": 0, "flash_assists": 0, "headshots": 8, "k_d_diff": -1, "kast": 65.2, "kills": 14, "rating": 1.1, "start_ct": 1, "total_rounds": 23, "win": 0, "r1_win": 1, "r2_win": 1, "r16_win": 1, "r17_win": 1, "h1_win_round_count": 5, "h2_win_round_count": 2, "h1_eliminated_count": 9, "h1_exploded_count": 4, "h1_defused_count": 2, "h1_timeout_count": 0, "h2_eliminated_count": 7, "h2_exploded_count": 0, "h2_defused_count": 0, "h2_timeout_count": 1}, {"game_id": 24736, "begin_at": "2020-08-02 11:33:39+00:00", "timestamp": 1596368019, "year": 2020, "month": 8, "day": 2, "weekday": 6, "hour": 11, "map_id": 2, "team_id": 127690, "player_id": 29507, "team_opponent_id": 127044, "player_opponent_id": 26692, "adr": 86.0, "assists": 3, "deaths": 15, "first_kills_diff": 0, "flash_assists": 0, "headshots": 8, "k_d_diff": -1, "kast": 65.2, "kills": 14, "rating": 1.1, "start_ct": 1, "total_rounds": 23, "win": 0, "r1_win": 1, "r2_win": 1, "r16_win": 1, "r17_win": 1, "h1_win_round_count": 5, "h2_win_round_count": 2, "h1_eliminated_count": 9, "h1_exploded_count": 4, "h1_defused_count": 2, "h1_timeout_count": 0, "h2_eliminated_count": 7, "h2_exploded_count": 0, "h2_defused_count": 0, "h2_timeout_count": 1}, {"game_id": 24736, "begin_at": "2020-08-02 11:33:39+00:00", "timestamp": 1596368019, "year": 2020, "month": 8, "day": 2, "weekday": 6, "hour": 11, "map_id": 2, "team_id": 127690, "player_id": 29507, "team_opponent_id": 127044, "player_opponent_id": 26693, "adr": 86.0, "assists": 3, "deaths": 15, "first_kills_diff": 0, "flash_assists": 0, "headshots": 8, "k_d_diff": -1, "kast": 65.2, "kills": 14, "rating": 1.1, "start_ct": 1, "total_rounds": 23, "win": 0, "r1_win": 1, "r2_win": 1, "r16_win": 1, "r17_win": 1, "h1_win_round_count": 5, "h2_win_round_count": 2, "h1_eliminated_count": 9, "h1_exploded_count": 4, "h1_defused_count": 2, "h1_timeout_count": 0, "h2_eliminated_count": 7, "h2_exploded_count": 0, "h2_defused_count": 0, "h2_timeout_count": 1}, {"game_id": 24736, "begin_at": "2020-08-02 11:33:39+00:00", "timestamp": 1596368019, "year": 2020, "month": 8, "day": 2, "weekday": 6, "hour": 11, "map_id": 2, "team_id": 127690, "player_id": 29508, "team_opponent_id": 127044, "player_opponent_id": 26689, "adr": 59.3, "assists": 1, "deaths": 15, "first_kills_diff": 1, "flash_assists": 0, "headshots": 5, "k_d_diff": 0, "kast": 69.6, "kills": 15, "rating": 0.93, "start_ct": 1, "total_rounds": 23, "win": 0, "r1_win": 1, "r2_win": 1, "r16_win": 1, "r17_win": 1, "h1_win_round_count": 5, "h2_win_round_count": 2, "h1_eliminated_count": 9, "h1_exploded_count": 4, "h1_defused_count": 2, "h1_timeout_count": 0, "h2_eliminated_count": 7, "h2_exploded_count": 0, "h2_defused_count": 0, "h2_timeout_count": 1}, {"game_id": 24736, "begin_at": "2020-08-02 11:33:39+00:00", "timestamp": 1596368019, "year": 2020, "month": 8, "day": 2, "weekday": 6, "hour": 11, "map_id": 2, "team_id": 127690, "player_id": 29508, "team_opponent_id": 127044, "player_opponent_id": 26690, "adr": 59.3, "assists": 1, "deaths": 15, "first_kills_diff": 1, "flash_assists": 0, "headshots": 5, "k_d_diff": 0, "kast": 69.6, "kills": 15, "rating": 0.93, "start_ct": 1, "total_rounds": 23, "win": 0, "r1_win": 1, "r2_win": 1, "r16_win": 1, "r17_win": 1, "h1_win_round_count": 5, "h2_win_round_count": 2, "h1_eliminated_count": 9, "h1_exploded_count": 4, "h1_defused_count": 2, "h1_timeout_count": 0, "h2_eliminated_count": 7, "h2_exploded_count": 0, "h2_defused_count": 0, "h2_timeout_count": 1}, {"game_id": 24736, "begin_at": "2020-08-02 11:33:39+00:00", "timestamp": 1596368019, "year": 2020, "month": 8, "day": 2, "weekday": 6, "hour": 11, "map_id": 2, "team_id": 127690, "player_id": 29508, "team_opponent_id": 127044, "player_opponent_id": 26691, "adr": 59.3, "assists": 1, "deaths": 15, "first_kills_diff": 1, "flash_assists": 0, "headshots": 5, "k_d_diff": 0, "kast": 69.6, "kills": 15, "rating": 0.93, "start_ct": 1, "total_rounds": 23, "win": 0, "r1_win": 1, "r2_win": 1, "r16_win": 1, "r17_win": 1, "h1_win_round_count": 5, "h2_win_round_count": 2, "h1_eliminated_count": 9, "h1_exploded_count": 4, "h1_defused_count": 2, "h1_timeout_count": 0, "h2_eliminated_count": 7, "h2_exploded_count": 0, "h2_defused_count": 0, "h2_timeout_count": 1}, {"game_id": 24736, "begin_at": "2020-08-02 11:33:39+00:00", "timestamp": 1596368019, "year": 2020, "month": 8, "day": 2, "weekday": 6, "hour": 11, "map_id": 2, "team_id": 127690, "player_id": 29508, "team_opponent_id": 127044, "player_opponent_id": 26692, "adr": 59.3, "assists": 1, "deaths": 15, "first_kills_diff": 1, "flash_assists": 0, "headshots": 5, "k_d_diff": 0, "kast": 69.6, "kills": 15, "rating": 0.93, "start_ct": 1, "total_rounds": 23, "win": 0, "r1_win": 1, "r2_win": 1, "r16_win": 1, "r17_win": 1, "h1_win_round_count": 5, "h2_win_round_count": 2, "h1_eliminated_count": 9, "h1_exploded_count": 4, "h1_defused_count": 2, "h1_timeout_count": 0, "h2_eliminated_count": 7, "h2_exploded_count": 0, "h2_defused_count": 0, "h2_timeout_count": 1}, {"game_id": 24736, "begin_at": "2020-08-02 11:33:39+00:00", "timestamp": 1596368019, "year": 2020, "month": 8, "day": 2, "weekday": 6, "hour": 11, "map_id": 2, "team_id": 127690, "player_id": 29508, "team_opponent_id": 127044, "player_opponent_id": 26693, "adr": 59.3, "assists": 1, "deaths": 15, "first_kills_diff": 1, "flash_assists": 0, "headshots": 5, "k_d_diff": 0, "kast": 69.6, "kills": 15, "rating": 0.93, "start_ct": 1, "total_rounds": 23, "win": 0, "r1_win": 1, "r2_win": 1, "r16_win": 1, "r17_win": 1, "h1_win_round_count": 5, "h2_win_round_count": 2, "h1_eliminated_count": 9, "h1_exploded_count": 4, "h1_defused_count": 2, "h1_timeout_count": 0, "h2_eliminated_count": 7, "h2_exploded_count": 0, "h2_defused_count": 0, "h2_timeout_count": 1}, {"game_id": 24736, "begin_at": "2020-08-02 11:33:39+00:00", "timestamp": 1596368019, "year": 2020, "month": 8, "day": 2, "weekday": 6, "hour": 11, "map_id": 2, "team_id": 127690, "player_id": 29509, "team_opponent_id": 127044, "player_opponent_id": 26689, "adr": 56.8, "assists": 3, "deaths": 15, "first_kills_diff": -1, "flash_assists": 0, "headshots": 4, "k_d_diff": -5, "kast": 65.2, "kills": 10, "rating": 0.76, "start_ct": 1, "total_rounds": 23, "win": 0, "r1_win": 1, "r2_win": 1, "r16_win": 1, "r17_win": 1, "h1_win_round_count": 5, "h2_win_round_count": 2, "h1_eliminated_count": 9, "h1_exploded_count": 4, "h1_defused_count": 2, "h1_timeout_count": 0, "h2_eliminated_count": 7, "h2_exploded_count": 0, "h2_defused_count": 0, "h2_timeout_count": 1}, {"game_id": 24736, "begin_at": "2020-08-02 11:33:39+00:00", "timestamp": 1596368019, "year": 2020, "month": 8, "day": 2, "weekday": 6, "hour": 11, "map_id": 2, "team_id": 127690, "player_id": 29509, "team_opponent_id": 127044, "player_opponent_id": 26690, "adr": 56.8, "assists": 3, "deaths": 15, "first_kills_diff": -1, "flash_assists": 0, "headshots": 4, "k_d_diff": -5, "kast": 65.2, "kills": 10, "rating": 0.76, "start_ct": 1, "total_rounds": 23, "win": 0, "r1_win": 1, "r2_win": 1, "r16_win": 1, "r17_win": 1, "h1_win_round_count": 5, "h2_win_round_count": 2, "h1_eliminated_count": 9, "h1_exploded_count": 4, "h1_defused_count": 2, "h1_timeout_count": 0, "h2_eliminated_count": 7, "h2_exploded_count": 0, "h2_defused_count": 0, "h2_timeout_count": 1}, {"game_id": 24736, "begin_at": "2020-08-02 11:33:39+00:00", "timestamp": 1596368019, "year": 2020, "month": 8, "day": 2, "weekday": 6, "hour": 11, "map_id": 2, "team_id": 127690, "player_id": 29509, "team_opponent_id": 127044, "player_opponent_id": 26691, "adr": 56.8, "assists": 3, "deaths": 15, "first_kills_diff": -1, "flash_assists": 0, "headshots": 4, "k_d_diff": -5, "kast": 65.2, "kills": 10, "rating": 0.76, "start_ct": 1, "total_rounds": 23, "win": 0, "r1_win": 1, "r2_win": 1, "r16_win": 1, "r17_win": 1, "h1_win_round_count": 5, "h2_win_round_count": 2, "h1_eliminated_count": 9, "h1_exploded_count": 4, "h1_defused_count": 2, "h1_timeout_count": 0, "h2_eliminated_count": 7, "h2_exploded_count": 0, "h2_defused_count": 0, "h2_timeout_count": 1}, {"game_id": 24736, "begin_at": "2020-08-02 11:33:39+00:00", "timestamp": 1596368019, "year": 2020, "month": 8, "day": 2, "weekday": 6, "hour": 11, "map_id": 2, "team_id": 127690, "player_id": 29509, "team_opponent_id": 127044, "player_opponent_id": 26692, "adr": 56.8, "assists": 3, "deaths": 15, "first_kills_diff": -1, "flash_assists": 0, "headshots": 4, "k_d_diff": -5, "kast": 65.2, "kills": 10, "rating": 0.76, "start_ct": 1, "total_rounds": 23, "win": 0, "r1_win": 1, "r2_win": 1, "r16_win": 1, "r17_win": 1, "h1_win_round_count": 5, "h2_win_round_count": 2, "h1_eliminated_count": 9, "h1_exploded_count": 4, "h1_defused_count": 2, "h1_timeout_count": 0, "h2_eliminated_count": 7, "h2_exploded_count": 0, "h2_defused_count": 0, "h2_timeout_count": 1}, {"game_id": 24736, "begin_at": "2020-08-02 11:33:39+00:00", "timestamp": 1596368019, "year": 2020, "month": 8, "day": 2, "weekday": 6, "hour": 11, "map_id": 2, "team_id": 127690, "player_id": 29509, "team_opponent_id": 127044, "player_opponent_id": 26693, "adr": 56.8, "assists": 3, "deaths": 15, "first_kills_diff": -1, "flash_assists": 0, "headshots": 4, "k_d_diff": -5, "kast": 65.2, "kills": 10, "rating": 0.76, "start_ct": 1, "total_rounds": 23, "win": 0, "r1_win": 1, "r2_win": 1, "r16_win": 1, "r17_win": 1, "h1_win_round_count": 5, "h2_win_round_count": 2, "h1_eliminated_count": 9, "h1_exploded_count": 4, "h1_defused_count": 2, "h1_timeout_count": 0, "h2_eliminated_count": 7, "h2_exploded_count": 0, "h2_defused_count": 0, "h2_timeout_count": 1}, {"game_id": 24736, "begin_at": "2020-08-02 11:33:39+00:00", "timestamp": 1596368019, "year": 2020, "month": 8, "day": 2, "weekday": 6, "hour": 11, "map_id": 2, "team_id": 127690, "player_id": 29510, "team_opponent_id": 127044, "player_opponent_id": 26689, "adr": 62.7, "assists": 1, "deaths": 19, "first_kills_diff": -1, "flash_assists": 0, "headshots": 8, "k_d_diff": -5, "kast": 60.9, "kills": 14, "rating": 0.69, "start_ct": 1, "total_rounds": 23, "win": 0, "r1_win": 1, "r2_win": 1, "r16_win": 1, "r17_win": 1, "h1_win_round_count": 5, "h2_win_round_count": 2, "h1_eliminated_count": 9, "h1_exploded_count": 4, "h1_defused_count": 2, "h1_timeout_count": 0, "h2_eliminated_count": 7, "h2_exploded_count": 0, "h2_defused_count": 0, "h2_timeout_count": 1}, {"game_id": 24736, "begin_at": "2020-08-02 11:33:39+00:00", "timestamp": 1596368019, "year": 2020, "month": 8, "day": 2, "weekday": 6, "hour": 11, "map_id": 2, "team_id": 127690, "player_id": 29510, "team_opponent_id": 127044, "player_opponent_id": 26690, "adr": 62.7, "assists": 1, "deaths": 19, "first_kills_diff": -1, "flash_assists": 0, "headshots": 8, "k_d_diff": -5, "kast": 60.9, "kills": 14, "rating": 0.69, "start_ct": 1, "total_rounds": 23, "win": 0, "r1_win": 1, "r2_win": 1, "r16_win": 1, "r17_win": 1, "h1_win_round_count": 5, "h2_win_round_count": 2, "h1_eliminated_count": 9, "h1_exploded_count": 4, "h1_defused_count": 2, "h1_timeout_count": 0, "h2_eliminated_count": 7, "h2_exploded_count": 0, "h2_defused_count": 0, "h2_timeout_count": 1}, {"game_id": 24736, "begin_at": "2020-08-02 11:33:39+00:00", "timestamp": 1596368019, "year": 2020, "month": 8, "day": 2, "weekday": 6, "hour": 11, "map_id": 2, "team_id": 127690, "player_id": 29510, "team_opponent_id": 127044, "player_opponent_id": 26691, "adr": 62.7, "assists": 1, "deaths": 19, "first_kills_diff": -1, "flash_assists": 0, "headshots": 8, "k_d_diff": -5, "kast": 60.9, "kills": 14, "rating": 0.69, "start_ct": 1, "total_rounds": 23, "win": 0, "r1_win": 1, "r2_win": 1, "r16_win": 1, "r17_win": 1, "h1_win_round_count": 5, "h2_win_round_count": 2, "h1_eliminated_count": 9, "h1_exploded_count": 4, "h1_defused_count": 2, "h1_timeout_count": 0, "h2_eliminated_count": 7, "h2_exploded_count": 0, "h2_defused_count": 0, "h2_timeout_count": 1}, {"game_id": 24736, "begin_at": "2020-08-02 11:33:39+00:00", "timestamp": 1596368019, "year": 2020, "month": 8, "day": 2, "weekday": 6, "hour": 11, "map_id": 2, "team_id": 127690, "player_id": 29510, "team_opponent_id": 127044, "player_opponent_id": 26692, "adr": 62.7, "assists": 1, "deaths": 19, "first_kills_diff": -1, "flash_assists": 0, "headshots": 8, "k_d_diff": -5, "kast": 60.9, "kills": 14, "rating": 0.69, "start_ct": 1, "total_rounds": 23, "win": 0, "r1_win": 1, "r2_win": 1, "r16_win": 1, "r17_win": 1, "h1_win_round_count": 5, "h2_win_round_count": 2, "h1_eliminated_count": 9, "h1_exploded_count": 4, "h1_defused_count": 2, "h1_timeout_count": 0, "h2_eliminated_count": 7, "h2_exploded_count": 0, "h2_defused_count": 0, "h2_timeout_count": 1}, {"game_id": 24736, "begin_at": "2020-08-02 11:33:39+00:00", "timestamp": 1596368019, "year": 2020, "month": 8, "day": 2, "weekday": 6, "hour": 11, "map_id": 2, "team_id": 127690, "player_id": 29510, "team_opponent_id": 127044, "player_opponent_id": 26693, "adr": 62.7, "assists": 1, "deaths": 19, "first_kills_diff": -1, "flash_assists": 0, "headshots": 8, "k_d_diff": -5, "kast": 60.9, "kills": 14, "rating": 0.69, "start_ct": 1, "total_rounds": 23, "win": 0, "r1_win": 1, "r2_win": 1, "r16_win": 1, "r17_win": 1, "h1_win_round_count": 5, "h2_win_round_count": 2, "h1_eliminated_count": 9, "h1_exploded_count": 4, "h1_defused_count": 2, "h1_timeout_count": 0, "h2_eliminated_count": 7, "h2_exploded_count": 0, "h2_defused_count": 0, "h2_timeout_count": 1}, {"game_id": 24736, "begin_at": "2020-08-02 11:33:39+00:00", "timestamp": 1596368019, "year": 2020, "month": 8, "day": 2, "weekday": 6, "hour": 11, "map_id": 2, "team_id": 127690, "player_id": 29511, "team_opponent_id": 127044, "player_opponent_id": 26689, "adr": 35.3, "assists": 1, "deaths": 18, "first_kills_diff": 0, "flash_assists": 0, "headshots": 3, "k_d_diff": -11, "kast": 47.8, "kills": 7, "rating": 0.54, "start_ct": 1, "total_rounds": 23, "win": 0, "r1_win": 1, "r2_win": 1, "r16_win": 1, "r17_win": 1, "h1_win_round_count": 5, "h2_win_round_count": 2, "h1_eliminated_count": 9, "h1_exploded_count": 4, "h1_defused_count": 2, "h1_timeout_count": 0, "h2_eliminated_count": 7, "h2_exploded_count": 0, "h2_defused_count": 0, "h2_timeout_count": 1}, {"game_id": 24736, "begin_at": "2020-08-02 11:33:39+00:00", "timestamp": 1596368019, "year": 2020, "month": 8, "day": 2, "weekday": 6, "hour": 11, "map_id": 2, "team_id": 127690, "player_id": 29511, "team_opponent_id": 127044, "player_opponent_id": 26690, "adr": 35.3, "assists": 1, "deaths": 18, "first_kills_diff": 0, "flash_assists": 0, "headshots": 3, "k_d_diff": -11, "kast": 47.8, "kills": 7, "rating": 0.54, "start_ct": 1, "total_rounds": 23, "win": 0, "r1_win": 1, "r2_win": 1, "r16_win": 1, "r17_win": 1, "h1_win_round_count": 5, "h2_win_round_count": 2, "h1_eliminated_count": 9, "h1_exploded_count": 4, "h1_defused_count": 2, "h1_timeout_count": 0, "h2_eliminated_count": 7, "h2_exploded_count": 0, "h2_defused_count": 0, "h2_timeout_count": 1}, {"game_id": 24736, "begin_at": "2020-08-02 11:33:39+00:00", "timestamp": 1596368019, "year": 2020, "month": 8, "day": 2, "weekday": 6, "hour": 11, "map_id": 2, "team_id": 127690, "player_id": 29511, "team_opponent_id": 127044, "player_opponent_id": 26691, "adr": 35.3, "assists": 1, "deaths": 18, "first_kills_diff": 0, "flash_assists": 0, "headshots": 3, "k_d_diff": -11, "kast": 47.8, "kills": 7, "rating": 0.54, "start_ct": 1, "total_rounds": 23, "win": 0, "r1_win": 1, "r2_win": 1, "r16_win": 1, "r17_win": 1, "h1_win_round_count": 5, "h2_win_round_count": 2, "h1_eliminated_count": 9, "h1_exploded_count": 4, "h1_defused_count": 2, "h1_timeout_count": 0, "h2_eliminated_count": 7, "h2_exploded_count": 0, "h2_defused_count": 0, "h2_timeout_count": 1}, {"game_id": 24736, "begin_at": "2020-08-02 11:33:39+00:00", "timestamp": 1596368019, "year": 2020, "month": 8, "day": 2, "weekday": 6, "hour": 11, "map_id": 2, "team_id": 127690, "player_id": 29511, "team_opponent_id": 127044, "player_opponent_id": 26692, "adr": 35.3, "assists": 1, "deaths": 18, "first_kills_diff": 0, "flash_assists": 0, "headshots": 3, "k_d_diff": -11, "kast": 47.8, "kills": 7, "rating": 0.54, "start_ct": 1, "total_rounds": 23, "win": 0, "r1_win": 1, "r2_win": 1, "r16_win": 1, "r17_win": 1, "h1_win_round_count": 5, "h2_win_round_count": 2, "h1_eliminated_count": 9, "h1_exploded_count": 4, "h1_defused_count": 2, "h1_timeout_count": 0, "h2_eliminated_count": 7, "h2_exploded_count": 0, "h2_defused_count": 0, "h2_timeout_count": 1}, {"game_id": 24736, "begin_at": "2020-08-02 11:33:39+00:00", "timestamp": 1596368019, "year": 2020, "month": 8, "day": 2, "weekday": 6, "hour": 11, "map_id": 2, "team_id": 127690, "player_id": 29511, "team_opponent_id": 127044, "player_opponent_id": 26693, "adr": 35.3, "assists": 1, "deaths": 18, "first_kills_diff": 0, "flash_assists": 0, "headshots": 3, "k_d_diff": -11, "kast": 47.8, "kills": 7, "rating": 0.54, "start_ct": 1, "total_rounds": 23, "win": 0, "r1_win": 1, "r2_win": 1, "r16_win": 1, "r17_win": 1, "h1_win_round_count": 5, "h2_win_round_count": 2, "h1_eliminated_count": 9, "h1_exploded_count": 4, "h1_defused_count": 2, "h1_timeout_count": 0, "h2_eliminated_count": 7, "h2_exploded_count": 0, "h2_defused_count": 0, "h2_timeout_count": 1}]